mia/__init__.py
mia/abc.py
mia/config.py
mia/containers.py
mia/exceptions.py
mia/log.py
mia/runner.py
mia/scripts.py
mia/cli/__init__.py
mia/cli/commands.py
mia/cli/main.py
mia/cli/run.py
mia/rpc/__init__.py
mia/rpc/consumer.py
mia/rpc/events.py
mia/rpc/message.py
mia/rpc/proxy.py
mia/rpc/publisher.py
mia/socket/__init__.py
mia/socket/func.py
mia/testing/__init__.py
mia/testing/pytest.py
mia/testing/utils.py
mia/timer/__init__.py
mia/utils/__init__.py
mia/utils/concurrency.py
mia/utils/helper.py
mia_zq-0.0.3.dist-info/METADATA
mia_zq-0.0.3.dist-info/WHEEL
mia_zq-0.0.3.dist-info/entry_points.txt
mia_zq-0.0.3.dist-info/top_level.txt
mia_zq-0.0.3.dist-info/zip-safe
mia_zq-0.0.3.dist-info/RECORD
